README.md
setup.py
c2j/__init__.py
c2j/transform.py
c2j.egg-info/PKG-INFO
c2j.egg-info/SOURCES.txt
c2j.egg-info/dependency_links.txt
c2j.egg-info/requires.txt
c2j.egg-info/top_level.txt
tests/__init__.py
tests/test_c2j.py