Metadata-Version: 2.1
Name: c2j
Version: 1.0.0
Summary: .csv-.json transformator
Home-page: https://github.com/3vlasenkov20/c2j
Author: Vlasenkov A.S.
Author-email: 3vlasenkov20@mail.ru
License: UNKNOWN
Platform: any
Requires-Python: >=3.7
